runledger/__init__.py
runledger/__main__.py
runledger/cli.py
runledger/artifacts/__init__.py
runledger/artifacts/junit.py
runledger/artifacts/report.py
runledger/artifacts/run_log.py
runledger/artifacts/summary.py
runledger/assertions/__init__.py
runledger/assertions/base.py
runledger/assertions/engine.py
runledger/assertions/json_schema.py
runledger/assertions/required_fields.py
runledger/assertions/tool_contract.py
runledger/baseline/__init__.py
runledger/baseline/io.py
runledger/baseline/models.py
runledger/cassette/__init__.py
runledger/cassette/loader.py
runledger/cassette/match.py
runledger/cassette/models.py
runledger/cassette/writer.py
runledger/config/__init__.py
runledger/config/loader.py
runledger/config/models.py
runledger/protocol/__init__.py
runledger/protocol/jsonl.py
runledger/protocol/messages.py
runledger/regression/__init__.py
runledger/regression/engine.py
runledger/runner/__init__.py
runledger/runner/budgets.py
runledger/runner/engine.py
runledger/runner/models.py
runledger/runner/subprocess.py
runledger/tools/__init__.py
runledger/tools/builtin.py
runledger/tools/registry.py
runledger/util/__init__.py
runledger/util/canonical_json.py
runledger/util/redaction.py
runledger-0.1.1.dist-info/licenses/LICENSE
runledger-0.1.1.dist-info/METADATA
runledger-0.1.1.dist-info/WHEEL
runledger-0.1.1.dist-info/entry_points.txt
runledger-0.1.1.dist-info/top_level.txt
runledger-0.1.1.dist-info/RECORD
