Metadata-Version: 2.4
Name: runledger
Version: 0.1.1
Summary: CI for tool-using agents: deterministic eval suites with record/replay, hard assertions, budgets, and PR regression gates.
Author: RunLedger
License: MIT License
Keywords: llm,agents,evaluation,ci,github-actions,replay,testing,junit,jsonschema
Requires-Python: >=3.9
License-File: LICENSE
Requires-Dist: typer>=0.9.0
Requires-Dist: rich>=13.0.0
Requires-Dist: pydantic>=2.0.0
Requires-Dist: pyyaml>=6.0.0
Requires-Dist: jsonschema>=4.0.0
Requires-Dist: jinja2>=3.1.0
Provides-Extra: dev
Requires-Dist: pytest>=7.0.0; extra == "dev"
Requires-Dist: pytest-timeout>=2.1.0; extra == "dev"
Requires-Dist: ruff>=0.1.0; extra == "dev"
Requires-Dist: mypy>=1.0.0; extra == "dev"
Dynamic: license-file
